{
    "annotations": {
      "list": [
        {
          "builtIn": 1,
          "datasource": {
            "type": "grafana",
            "uid": "-- Grafana --"
          },
          "enable": true,
          "hide": true,
          "iconColor": "rgba(0, 211, 255, 1)",
          "name": "Annotations & Alerts",
          "type": "dashboard"
        }
      ]
    },
    "editable": true,
    "fiscalYearStartMonth": 0,
    "graphTooltip": 0,
    "id": 6,
    "links": [],
    "liveNow": false,
    "panels": [
      {
        "datasource": {
          "type": "prometheus",
          "uid": "PBFA97CFB590B2093"
        },
        "fieldConfig": {
          "defaults": {
            "color": {
              "mode": "continuous-RdYlGr"
            },
            "mappings": [],
            "thresholds": {
              "mode": "absolute",
              "steps": [
                {
                  "color": "green",
                  "value": null
                }
              ]
            }
          },
          "overrides": []
        },
        "gridPos": {
          "h": 7,
          "w": 15,
          "x": 0,
          "y": 0
        },
        "id": 1,
        "interval": "5s",
        "options": {
          "colorMode": "value",
          "graphMode": "area",
          "justifyMode": "auto",
          "orientation": "auto",
          "reduceOptions": {
            "calcs": [
              "lastNotNull"
            ],
            "fields": "",
            "values": false
          },
          "textMode": "auto"
        },
        "pluginVersion": "9.5.12",
        "targets": [
          {
            "datasource": {
              "type": "prometheus",
              "uid": "PBFA97CFB590B2093"
            },
            "editorMode": "builder",
            "expr": "chain_head_block",
            "legendFormat": "{{job}}",
            "range": true,
            "refId": "A"
          },
          {
            "datasource": {
              "type": "prometheus",
              "uid": "PBFA97CFB590B2093"
            },
            "editorMode": "builder",
            "expr": "reth_blockchain_tree_canonical_chain_height",
            "hide": false,
            "legendFormat": "{{job}}",
            "range": true,
            "refId": "B"
          },
          {
            "datasource": {
              "type": "prometheus",
              "uid": "PBFA97CFB590B2093"
            },
            "editorMode": "builder",
            "expr": "nethermind_blocks",
            "hide": false,
            "legendFormat": "{{job}}",
            "range": true,
            "refId": "C"
          }
        ],
        "title": "Panel Title",
        "type": "stat"
      }
    ],
    "refresh": "",
    "schemaVersion": 38,
    "style": "dark",
    "tags": [],
    "templating": {
      "list": []
    },
    "time": {
      "from": "now-6h",
      "to": "now"
    },
    "timepicker": {},
    "timezone": "",
    "title": "All Execution Board",
    "uid": "bb16fc68-edd8-423a-ba1d-c28efce4e22a",
    "version": 2,
    "weekStart": ""
  }